{
    "Abhi": {
        "name": "Abhi",
        "education_level": "College",
        "grade": null,
        "grades": {
            "co": 95,
            "cn": 100,
            "cd": 100,
            "se": 94
        },
        "subjects": [
            "co",
            "cn",
            "cd",
            "se"
        ],
        "progress": {},
        "taught_concepts": {
            "co": [],
            "cn": [],
            "cd": [],
            "se": []
        }
    },
    "Abhigna": {
        "name": "Abhigna",
        "education_level": "College",
        "grade": null,
        "grades": {
            "AI": 100,
            "Maths": 100,
            "Science": 100
        },
        "subjects": [
            "AI",
            "Maths",
            "Science"
        ],
        "progress": {
            "AI": [
                {
                    "score": 33.33,
                    "correct": 1
                }
            ]
        },
        "taught_concepts": {
            "AI": [
                "Adversarial Reinforcement Learning"
            ],
            "Maths": [],
            "Science": []
        },
        "levels": {}
    },
    "Sony": {
        "name": "Sony",
        "education_level": "School",
        "grade": "Grade 1",
        "grades": {
            "English": 100,
            "Mathematics": 100,
            "Science": 100,
            "Social Studies": 100
        },
        "subjects": [
            "English",
            "Mathematics",
            "Science",
            "Social Studies"
        ],
        "progress": {
            "Mathematics": [
                {
                    "score": 66.67,
                    "correct": 2
                }
            ]
        },
        "taught_concepts": {
            "English": [],
            "Mathematics": [
                "Multivariable Optimization with Lagrange Multipliers"
            ],
            "Science": [],
            "Social Studies": []
        },
        "levels": {}
    }
}